Metadata-Version: 1.0
Name: calc-plot-distributions
Version: 1.0.0
Summary: Gaussian distributions
Home-page: UNKNOWN
Author: Ezeobi Jeshurun
Author-email: oejeshurun@gmail.com
License: UNKNOWN
Platform: UNKNOWN
